flexible_schema/__init__.py
flexible_schema/base.py
flexible_schema/columns.py
flexible_schema/exceptions.py
flexible_schema/json.py
flexible_schema/pyarrow.py
flexible_schema-0.1.1.dist-info/licenses/LICENSE
flexible_schema-0.1.1.dist-info/METADATA
flexible_schema-0.1.1.dist-info/WHEEL
flexible_schema-0.1.1.dist-info/top_level.txt
flexible_schema-0.1.1.dist-info/RECORD
