Metadata-Version: 2.4
Name: flexible_schema
Version: 0.1.1
Summary: A simple class to aid in defining flexible schemas for PyArrow datasets.
Author-email: Matthew McDermott <mattmcdermott8@gmail.com>
Project-URL: Homepage, https://github.com/mmcdermott/flexible_schema
Project-URL: Issues, https://github.com/mmcdermott/flexible_schema/issues
Classifier: Programming Language :: Python :: 3
Classifier: License :: OSI Approved :: MIT License
Classifier: Operating System :: OS Independent
Requires-Python: >=3.10
License-File: LICENSE
Requires-Dist: pyarrow>=8
Requires-Dist: jsonschema>=4.0.0
Requires-Dist: typing_extensions>=4.0
Provides-Extra: dev
Requires-Dist: pre-commit<4; extra == "dev"
Requires-Dist: ruff; extra == "dev"
Provides-Extra: tests
Requires-Dist: pytest; extra == "tests"
Requires-Dist: pytest-cov[toml]; extra == "tests"
Provides-Extra: docs
Requires-Dist: mkdocs==1.6.1; extra == "docs"
Requires-Dist: mkdocs-material==9.6.7; extra == "docs"
Requires-Dist: mkdocstrings[python,shell]==0.28.2; extra == "docs"
Requires-Dist: mkdocs-gen-files==0.5.0; extra == "docs"
Requires-Dist: mkdocs-literate-nav==0.6.1; extra == "docs"
Requires-Dist: mkdocs-section-index==0.3.9; extra == "docs"
Requires-Dist: mkdocs-git-authors-plugin==0.9.2; extra == "docs"
Requires-Dist: mkdocs-git-revision-date-localized-plugin==1.3.0; extra == "docs"
Requires-Dist: markdown-callouts; extra == "docs"
Dynamic: license-file
